dogpile_cachetool/__init__.py
dogpile_cachetool/__version__.py
dogpile_cachetool/core.py
dogpile_cachetool/testing.py
dogpile_cachetool/utils.py
dogpile_cachetool/backends/__init__.py
dogpile_cachetool/backends/debug.py
dogpile_cachetool/backends/redis_rc.py
dogpile_cachetool/backends/rediscluster.py
dogpile_cachetool/tests/__init__.py
dogpile_cachetool/tests/_fixtures.py
dogpile_cachetool/tests/test_cache.py
dogpile_cachetool/tests/test_decorator.py
dogpile_cachetool/tests/test_redis_rc_backend.py
dogpile_cachetool/tests/test_rediscluster_backend.py
dogpile_cachetool-0.3.1.dist-info/METADATA
dogpile_cachetool-0.3.1.dist-info/WHEEL
dogpile_cachetool-0.3.1.dist-info/top_level.txt
dogpile_cachetool-0.3.1.dist-info/RECORD
